README.md
setup.py
autoyaml/__init__.py
autoyaml/encryptor.py
autoyaml.egg-info/PKG-INFO
autoyaml.egg-info/SOURCES.txt
autoyaml.egg-info/dependency_links.txt
autoyaml.egg-info/requires.txt
autoyaml.egg-info/top_level.txt