Metadata-Version: 2.1
Name: autoyaml
Version: 2020.2.4.1552
Summary: Load and save config files for python projects
Home-page: https://github.com/martyni/autoyaml
Author: martyni
Author-email: martynjamespratt@gmail.com
License: MIT
Platform: UNKNOWN
Classifier: Programming Language :: Python :: 3.7
Classifier: Programming Language :: Python :: 3.6
Classifier: Programming Language :: Python :: 3.5
